{
    "no-assignee":
    {
        "receivers":
        [
            "calixte@mozilla.com",
            "sylvestre@mozilla.com"
        ],
        "days_lookup": 7,
        "reporter_exception":
        // the bugs where the reporter is in this list are not retrieved
        [
            "wptsync@mozilla.bugs"
        ]
    },
    "common":
    {
        "receivers":
        [
            "calixte@mozilla.com",
            "sylvestre@mozilla.com"
        ],
        "days_lookup": 7,
        "bz_query_timeout": 240
    },
    "unaffected_affected_no_reg":
    {
        "receivers":
        [
            "calixte@mozilla.com",
            "sylvestre@mozilla.com",
            "mcastelluccio@mozilla.com"
        ],
        "days_lookup": 7,
        "word_blacklist":
        [
            "[pP]ermafailing",
            "[pP]erma-failing",
            "[pP]erma ",
            "[iI]ntermittent ",
            "[bB]uild bustage",
            "[bB]ustages on"
        ]
    },
    "regression":
    {
        "receivers":
        [
            "calixte@mozilla.com",
            "sylvestre@mozilla.com",
            "mcastelluccio@mozilla.com"
        ],
        "days_lookup": 7,
        "product_blacklist":
        [
            "SeaMonkey",
            "Thunderbird",
            "Release Engineering",
            "Webtools"
        ],
        "resolution_blacklist":
        [
            "DUPLICATE"
        ]
    },
    "auto_nag":
    {
        "no_mail_for_manager":
        [
            "jgriffiths@mozilla.com"
        ]
    }
}
